borg_drone/__init__.py
borg_drone/__main__.py
borg_drone/command.py
borg_drone/config.py
borg_drone/example.yml
borg_drone/types.py
borg_drone/util.py
borg_drone-0.2.0.post0.dist-info/entry_points.txt
borg_drone-0.2.0.post0.dist-info/WHEEL
borg_drone-0.2.0.post0.dist-info/METADATA
borg_drone-0.2.0.post0.dist-info/RECORD
