Metadata-Version: 2.1
Name: borg-drone
Version: 0.2.0.post0
Summary: Yet another borg wrapper
Requires-Python: >=3.6
Requires-Dist: PyYAML ~= 6.0
Requires-Dist: typing-extensions == 4.7.0
Requires-Dist: yapf ; extra == "dev"
Requires-Dist: autoflake ; extra == "dev"
Requires-Dist: mypy ; extra == "dev"
Requires-Dist: flit ; extra == "dev"
Requires-Dist: toml ; extra == "dev"
Requires-Dist: pytest ; extra == "test"
Requires-Dist: pytest-cov ; extra == "test"
Provides-Extra: dev
Provides-Extra: test
